{"id": "qWAagS_MANg", "uploader": "Bon App\u00e9tit", "uploader_id": "BonAppetitDotCom", "uploader_url": "http://www.youtube.com/user/BonAppetitDotCom", "channel_id": "UCbpMy0Fg74eXXkvxJrtEn3w", "channel_url": "http://www.youtube.com/channel/UCbpMy0Fg74eXXkvxJrtEn3w", "upload_date": "20190325", "license": null, "creator": null, "title": "Every Way to Cook an Egg (59 Methods) | Bon App\u00e9tit", "alt_title": null, "thumbnail": "https://i.ytimg.com/vi/qWAagS_MANg/maxresdefault.jpg", "description": "Join Basically editor Amiel Stanek as he attempts to cook an egg in almost every way possible. Which method is the best? Can there be a best method? What does 'best' even mean? Who says what's best? Not us. They're all eggcelent (besides the ones that aren't).\n\nCheck out each of the methods here (thanks to Asaf Lebovic for making this list):\n0:47 raw egg\n1:10 prairie oyster\n1:34 amber moon\n2:00 sunny side up egg\n2:25 olive oil fried egg\n2:51 olive oil fried (basted) egg\n3:18 olive oil friend (steamed) egg\n3:43 over easy/medium/hard egg\n4:26 salt block fried egg\n4:41 McMuffin Egg\n4:58 cracked and scrambled egg\n5:30 low and slow scrambled egg\n6:00 hot and fast scrambled egg\n6:33 boiled egg\n7:39 steamed whole egg\n8:37 sous-vide egg\n9:08 pickled egg\n10:11 poached egg\n10:40 egg poached in tomato sauce\n11:14 microwave scrambled egg\n11:32 microwave poached egg\n11:52 grilled in George Foreman egg\n12:17 waffle iron egg\n12:46 blowtorched egg\n13:09 diner style omelet egg\n13:41 French omelet egg\n14:16 souffled omelet egg\n14:47 cloud egg\n15:20 steamed custard egg (Chinese style steamed egg custard)\n15:53 coddled egg\n16:26 shirred egg\n16:54 air fried egg\n17:31 deep-fried egg\n17:54 dehydrated egg\n18:18 frittata egg\n18:48 frozen egg\n19:17 dishwasher egg\n19:49 rice cooker egg\n20:22 egg cooker egg\n20:50 Rollie cooked egg\n21:18 oven cooked egg\n22:08 cooked in broth egg\n22:48 grilled egg\n23:13 smoked egg\n23:43 campfire (cast iron) egg\n24:19 campfire (foil pouch) egg\n24:49 campfire (burned in coals) egg\n25:11 sauna cooked egg\n\n\n\n\n25:38 engine cooked egg\n26:03 solar oven egg\n\nStill haven\u2019t subscribed to Bon Appetit on YouTube? \u25ba\u25ba http://bit.ly/1TLeyPn\n\nABOUT BON APP\u00c9TIT\nCook with confidence using Bon Appetit\u2019s kitchen tips, recipes, videos, and restaurant guides. Stay current on the latest food trends, dining destinations, and hosting ideas.\n\nEvery Way to Cook an Egg (59 Methods) | Bon App\u00e9tit", "categories": ["Howto & Style"], "tags": ["egg", "eggs", "every way", "every way to cook", "every type of egg", "amiel stanek", "amiel", "amiel bon appetit", "amiel makes", "amiel makes eggs", "how to cook", "make eggs", "making eggs", "cooking eggs", "cook eggs", "how to cook eggs", "how to make eggs", "best eggs", "best way to make eggs", "every way to cook eggs", "every way to make eggs", "scrambled eggs", "fried eggs", "poached eggs", "eggs benedict", "best eggs recipe", "omelet", "best omelet", "best scrambled eggs", "every", "way", "every way to make", "food", "bon appetit"], "subtitles": {}, "automatic_captions": {}, "duration": 1630, "age_limit": 0, "annotations": null, "chapters": [{"start_time": 47.0, "end_time": 70.0, "title": "raw egg"}, {"start_time": 70.0, "end_time": 120.0, "title": "prairie oyster"}, {"start_time": 120.0, "end_time": 145.0, "title": "sunny side up egg"}, {"start_time": 145.0, "end_time": 171.0, "title": "olive oil fried egg"}, {"start_time": 171.0, "end_time": 198.0, "title": "olive oil fried (basted) egg"}, {"start_time": 198.0, "end_time": 223.0, "title": "olive oil friend (steamed) egg"}, {"start_time": 223.0, "end_time": 266.0, "title": "over easy/medium/hard egg"}, {"start_time": 266.0, "end_time": 281.0, "title": "salt block fried egg"}, {"start_time": 281.0, "end_time": 298.0, "title": "McMuffin Egg"}, {"start_time": 298.0, "end_time": 330.0, "title": "cracked and scrambled egg"}, {"start_time": 330.0, "end_time": 360.0, "title": "low and slow scrambled egg"}, {"start_time": 360.0, "end_time": 393.0, "title": "hot and fast scrambled egg"}, {"start_time": 393.0, "end_time": 459.0, "title": "boiled egg"}, {"start_time": 459.0, "end_time": 517.0, "title": "steamed whole egg"}, {"start_time": 517.0, "end_time": 548.0, "title": "sous-vide egg"}, {"start_time": 548.0, "end_time": 611.0, "title": "pickled egg"}, {"start_time": 611.0, "end_time": 640.0, "title": "poached egg"}, {"start_time": 640.0, "end_time": 674.0, "title": "egg poached in tomato sauce"}, {"start_time": 674.0, "end_time": 692.0, "title": "microwave scrambled egg"}, {"start_time": 692.0, "end_time": 712.0, "title": "microwave poached egg"}, {"start_time": 712.0, "end_time": 737.0, "title": "grilled in George Foreman egg"}, {"start_time": 737.0, "end_time": 766.0, "title": "waffle iron egg"}, {"start_time": 766.0, "end_time": 789.0, "title": "blowtorched egg"}, {"start_time": 789.0, "end_time": 821.0, "title": "diner style omelet egg"}, {"start_time": 821.0, "end_time": 856.0, "title": "French omelet egg"}, {"start_time": 856.0, "end_time": 887.0, "title": "souffled omelet egg"}, {"start_time": 887.0, "end_time": 920.0, "title": "cloud egg"}, {"start_time": 920.0, "end_time": 953.0, "title": "steamed custard egg (Chinese style steamed egg custard)"}, {"start_time": 953.0, "end_time": 986.0, "title": "coddled egg"}, {"start_time": 986.0, "end_time": 1014.0, "title": "shirred egg"}, {"start_time": 1014.0, "end_time": 1051.0, "title": "air fried egg"}, {"start_time": 1051.0, "end_time": 1074.0, "title": "deep-fried egg"}, {"start_time": 1074.0, "end_time": 1098.0, "title": "dehydrated egg"}, {"start_time": 1098.0, "end_time": 1128.0, "title": "frittata egg"}, {"start_time": 1128.0, "end_time": 1157.0, "title": "frozen egg"}, {"start_time": 1157.0, "end_time": 1189.0, "title": "dishwasher egg"}, {"start_time": 1189.0, "end_time": 1222.0, "title": "rice cooker egg"}, {"start_time": 1222.0, "end_time": 1250.0, "title": "egg cooker egg"}, {"start_time": 1250.0, "end_time": 1278.0, "title": "Rollie cooked egg"}, {"start_time": 1278.0, "end_time": 1328.0, "title": "oven cooked egg"}, {"start_time": 1328.0, "end_time": 1368.0, "title": "cooked in broth egg"}, {"start_time": 1368.0, "end_time": 1393.0, "title": "grilled egg"}, {"start_time": 1393.0, "end_time": 1423.0, "title": "smoked egg"}, {"start_time": 1423.0, "end_time": 1459.0, "title": "campfire (cast iron) egg"}, {"start_time": 1459.0, "end_time": 1489.0, "title": "campfire (foil pouch) egg"}, {"start_time": 1489.0, "end_time": 1511.0, "title": "campfire (burned in coals) egg"}, {"start_time": 1511.0, "end_time": 1538.0, "title": "sauna cooked egg"}, {"start_time": 1538.0, "end_time": 1563.0, "title": "engine cooked egg"}, {"start_time": 1563.0, "end_time": 1630, "title": "solar oven egg"}], "webpage_url": "https://www.youtube.com/watch?v=qWAagS_MANg", "view_count": 14864782, "like_count": 316388, "dislike_count": 14722, "average_rating": 4.8221498, "formats": [{"format_id": "249", "url": "https://r5---sn-qxo7rn7l.googlevideo.com/videoplayback?expire=1565151721&ei=if1JXdmwHIy5igT5kKnIDg&ip=75.148.115.129&id=o-APep3WUvnBIUQs-4o6_aqmYdw6AUcs2c1j2F-6Jz7WsO&itag=249&source=youtube&requiressl=yes&mm=31%2C29&mn=sn-qxo7rn7l%2Csn-qxoedn7e&ms=au%2Crdu&mv=m&mvi=4&pl=20&initcwndbps=2182500&mime=audio%2Fwebm&gir=yes&clen=11016533&dur=1630.241&lmt=1553591580053253&mt=1565129957&fvip=5&keepalive=yes&c=WEB&txp=5511222&sparams=expire%2Cei%2Cip%2Cid%2Citag%2Csource%2Crequiressl%2Cmime%2Cgir%2Cclen%2Cdur%2Clmt&sig=ALgxI2wwRQIgIajr6jmJMFiwuqIpQxCLeJuYdd6yckhNV7N-_9CWapICIQDnijLGdxWxGsREd9mNqobc1fvrguHo2_sHUE1NJhHyog%3D%3D&lsparams=mm%2Cmn%2Cms%2Cmv%2Cmvi%2Cpl%2Cinitcwndbps&lsig=AHylml4wRQIhALfDth5wbLngxVSJRuRMR1H1JNniU1V4CoFDsWDAzxIkAiAU4Xx3ZGd1Z-1Oj-d0ZmVhccwGDodPwdabQYQHw07_eg%3D%3D&ratebypass=yes", "player_url": "/yts/jsbin/player_ias-vfl3cxFuT/en_US/base.js", "ext": "webm", "format_note": "DASH audio", "acodec": "opus", "abr": 50, "filesize": 11016533, "tbr": 66.631, "quality": -1, "vcodec": "none", "downloader_options": {"http_chunk_size": 10485760}, "format": "249 - audio only (DASH audio)", "protocol": "https", "http_headers": {"User-Agent": "Mozilla/5.0 (Windows NT 10.0; Win64; x64) AppleWebKit/537.36 (KHTML, like Gecko) Chrome/73.0.3639.0 Safari/537.36", "Accept-Charset": "ISO-8859-1,utf-8;q=0.7,*;q=0.7", "Accept": "text/html,application/xhtml+xml,application/xml;q=0.9,*/*;q=0.8", "Accept-Encoding": "gzip, deflate", "Accept-Language": "en-us,en;q=0.5"}}, {"format_id": "250", "url": "https://r5---sn-qxo7rn7l.googlevideo.com/videoplayback?expire=1565151721&ei=if1JXdmwHIy5igT5kKnIDg&ip=75.148.115.129&id=o-APep3WUvnBIUQs-4o6_aqmYdw6AUcs2c1j2F-6Jz7WsO&itag=250&source=youtube&requiressl=yes&mm=31%2C29&mn=sn-qxo7rn7l%2Csn-qxoedn7e&ms=au%2Crdu&mv=m&mvi=4&pl=20&initcwndbps=2182500&mime=audio%2Fwebm&gir=yes&clen=15835641&dur=1630.241&lmt=1553591561632926&mt=1565129957&fvip=5&keepalive=yes&c=WEB&txp=5511222&sparams=expire%2Cei%2Cip%2Cid%2Citag%2Csource%2Crequiressl%2Cmime%2Cgir%2Cclen%2Cdur%2Clmt&sig=ALgxI2wwRQIgdwlNLnijpxLTgDELoq-EYPnn-_YoiGOFDc36ODvq7iMCIQDeN1ldK_HJ_iwzOq6OKOFOJXYgRfoPDM5I0lCROeQBvw%3D%3D&lsparams=mm%2Cmn%2Cms%2Cmv%2Cmvi%2Cpl%2Cinitcwndbps&lsig=AHylml4wRQIhALfDth5wbLngxVSJRuRMR1H1JNniU1V4CoFDsWDAzxIkAiAU4Xx3ZGd1Z-1Oj-d0ZmVhccwGDodPwdabQYQHw07_eg%3D%3D&ratebypass=yes", "player_url": "/yts/jsbin/player_ias-vfl3cxFuT/en_US/base.js", "ext": "webm", "format_note": "DASH audio", "acodec": "opus", "abr": 70, "filesize": 15835641, "tbr": 89.403, "quality": -1, "vcodec": "none", "downloader_options": {"http_chunk_size": 10485760}, "format": "250 - audio only (DASH audio)", "protocol": "https", "http_headers": {"User-Agent": "Mozilla/5.0 (Windows NT 10.0; Win64; x64) AppleWebKit/537.36 (KHTML, like Gecko) Chrome/73.0.3639.0 Safari/537.36", "Accept-Charset": "ISO-8859-1,utf-8;q=0.7,*;q=0.7", "Accept": "text/html,application/xhtml+xml,application/xml;q=0.9,*/*;q=0.8", "Accept-Encoding": "gzip, deflate", "Accept-Language": "en-us,en;q=0.5"}}, {"format_id": "140", "url": "https://r5---sn-qxo7rn7l.googlevideo.com/videoplayback?expire=1565151721&ei=if1JXdmwHIy5igT5kKnIDg&ip=75.148.115.129&id=o-APep3WUvnBIUQs-4o6_aqmYdw6AUcs2c1j2F-6Jz7WsO&itag=140&source=youtube&requiressl=yes&mm=31%2C29&mn=sn-qxo7rn7l%2Csn-qxoedn7e&ms=au%2Crdu&mv=m&mvi=4&pl=20&initcwndbps=2182500&mime=audio%2Fmp4&gir=yes&clen=26384922&dur=1630.272&lmt=1553530770981983&mt=1565129957&fvip=5&keepalive=yes&c=WEB&txp=4531432&sparams=expire%2Cei%2Cip%2Cid%2Citag%2Csource%2Crequiressl%2Cmime%2Cgir%2Cclen%2Cdur%2Clmt&sig=ALgxI2wwRgIhANC5zSGOAB0qLIhrxxGBHLTLDrkwzewlBNmna-GW1YdTAiEAxKhiKn-lrg_2sK7e_7amBufYtOFPhChYgwEmJFtKo_8%3D&lsparams=mm%2Cmn%2Cms%2Cmv%2Cmvi%2Cpl%2Cinitcwndbps&lsig=AHylml4wRQIhALfDth5wbLngxVSJRuRMR1H1JNniU1V4CoFDsWDAzxIkAiAU4Xx3ZGd1Z-1Oj-d0ZmVhccwGDodPwdabQYQHw07_eg%3D%3D&ratebypass=yes", "player_url": "/yts/jsbin/player_ias-vfl3cxFuT/en_US/base.js", "ext": "m4a", "format_note": "DASH audio", "acodec": "mp4a.40.2", "abr": 128, "container": "m4a_dash", "filesize": 26384922, "tbr": 131.777, "quality": -1, "vcodec": "none", "downloader_options": {"http_chunk_size": 10485760}, "format": "140 - audio only (DASH audio)", "protocol": "https", "http_headers": {"User-Agent": "Mozilla/5.0 (Windows NT 10.0; Win64; x64) AppleWebKit/537.36 (KHTML, like Gecko) Chrome/73.0.3639.0 Safari/537.36", "Accept-Charset": "ISO-8859-1,utf-8;q=0.7,*;q=0.7", "Accept": "text/html,application/xhtml+xml,application/xml;q=0.9,*/*;q=0.8", "Accept-Encoding": "gzip, deflate", "Accept-Language": "en-us,en;q=0.5"}}, {"format_id": "251", "url": "https://r5---sn-qxo7rn7l.googlevideo.com/videoplayback?expire=1565151721&ei=if1JXdmwHIy5igT5kKnIDg&ip=75.148.115.129&id=o-APep3WUvnBIUQs-4o6_aqmYdw6AUcs2c1j2F-6Jz7WsO&itag=251&source=youtube&requiressl=yes&mm=31%2C29&mn=sn-qxo7rn7l%2Csn-qxoedn7e&ms=au%2Crdu&mv=m&mvi=4&pl=20&initcwndbps=2182500&mime=audio%2Fwebm&gir=yes&clen=29542464&dur=1630.241&lmt=1553591558037497&mt=1565129957&fvip=5&keepalive=yes&c=WEB&txp=5511222&sparams=expire%2Cei%2Cip%2Cid%2Citag%2Csource%2Crequiressl%2Cmime%2Cgir%2Cclen%2Cdur%2Clmt&sig=ALgxI2wwRgIhAIz6ZAkNq8s76z4IXlS0Mf_C0uHOSeh9Ma3CkcrzlgveAiEAhDiXQ-mmG6S43DtpUXM-ZHXUomUn9S5JUblp6K-UdQM%3D&lsparams=mm%2Cmn%2Cms%2Cmv%2Cmvi%2Cpl%2Cinitcwndbps&lsig=AHylml4wRQIhALfDth5wbLngxVSJRuRMR1H1JNniU1V4CoFDsWDAzxIkAiAU4Xx3ZGd1Z-1Oj-d0ZmVhccwGDodPwdabQYQHw07_eg%3D%3D&ratebypass=yes", "player_url": "/yts/jsbin/player_ias-vfl3cxFuT/en_US/base.js", "ext": "webm", "format_note": "DASH audio", "acodec": "opus", "abr": 160, "filesize": 29542464, "tbr": 165.964, "quality": -1, "vcodec": "none", "downloader_options": {"http_chunk_size": 10485760}, "format": "251 - audio only (DASH audio)", "protocol": "https", "http_headers": {"User-Agent": "Mozilla/5.0 (Windows NT 10.0; Win64; x64) AppleWebKit/537.36 (KHTML, like Gecko) Chrome/73.0.3639.0 Safari/537.36", "Accept-Charset": "ISO-8859-1,utf-8;q=0.7,*;q=0.7", "Accept": "text/html,application/xhtml+xml,application/xml;q=0.9,*/*;q=0.8", "Accept-Encoding": "gzip, deflate", "Accept-Language": "en-us,en;q=0.5"}}, {"format_id": "394", "url": "https://r5---sn-qxo7rn7l.googlevideo.com/videoplayback?expire=1565151721&ei=if1JXdmwHIy5igT5kKnIDg&ip=75.148.115.129&id=o-APep3WUvnBIUQs-4o6_aqmYdw6AUcs2c1j2F-6Jz7WsO&itag=394&aitags=133%2C134%2C135%2C136%2C137%2C160%2C242%2C243%2C244%2C247%2C248%2C278%2C394%2C395%2C396%2C397%2C398&source=youtube&requiressl=yes&mm=31%2C29&mn=sn-qxo7rn7l%2Csn-qxoedn7e&ms=au%2Crdu&mv=m&mvi=4&pl=20&initcwndbps=2182500&mime=video%2Fmp4&gir=yes&clen=15911111&dur=1630.170&lmt=1553782887334709&mt=1565129957&fvip=5&keepalive=yes&c=WEB&txp=5531432&sparams=expire%2Cei%2Cip%2Cid%2Caitags%2Csource%2Crequiressl%2Cmime%2Cgir%2Cclen%2Cdur%2Clmt&sig=ALgxI2wwRQIgaznw2srW3_1DIei_q3tIVJLvH6VsxSirWDb2sOWurD0CIQDUz9ceDQ1RqzrwGpTYGHaGAJfo3N2Rm0oQo41_BKbCBQ%3D%3D&lsparams=mm%2Cmn%2Cms%2Cmv%2Cmvi%2Cpl%2Cinitcwndbps&lsig=AHylml4wRQIhALfDth5wbLngxVSJRuRMR1H1JNniU1V4CoFDsWDAzxIkAiAU4Xx3ZGd1Z-1Oj-d0ZmVhccwGDodPwdabQYQHw07_eg%3D%3D&ratebypass=yes", "player_url": "/yts/jsbin/player_ias-vfl3cxFuT/en_US/base.js", "acodec": "none", "vcodec": "av01.0.05M.08", "filesize": 15911111, "tbr": 91.487, "width": 256, "height": 144, "fps": 24, "format_note": "144p", "quality": -1, "ext": "mp4", "downloader_options": {"http_chunk_size": 10485760}, "format": "394 - 256x144 (144p)", "protocol": "https", "http_headers": {"User-Agent": "Mozilla/5.0 (Windows NT 10.0; Win64; x64) AppleWebKit/537.36 (KHTML, like Gecko) Chrome/73.0.3639.0 Safari/537.36", "Accept-Charset": "ISO-8859-1,utf-8;q=0.7,*;q=0.7", "Accept": "text/html,application/xhtml+xml,application/xml;q=0.9,*/*;q=0.8", "Accept-Encoding": "gzip, deflate", "Accept-Language": "en-us,en;q=0.5"}}, {"format_id": "160", "url": "https://r5---sn-qxo7rn7l.googlevideo.com/videoplayback?expire=1565151721&ei=if1JXdmwHIy5igT5kKnIDg&ip=75.148.115.129&id=o-APep3WUvnBIUQs-4o6_aqmYdw6AUcs2c1j2F-6Jz7WsO&itag=160&aitags=133%2C134%2C135%2C136%2C137%2C160%2C242%2C243%2C244%2C247%2C248%2C278%2C394%2C395%2C396%2C397%2C398&source=youtube&requiressl=yes&mm=31%2C29&mn=sn-qxo7rn7l%2Csn-qxoedn7e&ms=au%2Crdu&mv=m&mvi=4&pl=20&initcwndbps=2182500&mime=video%2Fmp4&gir=yes&clen=13840073&dur=1630.170&lmt=1553531072165203&mt=1565129957&fvip=5&keepalive=yes&c=WEB&txp=4535432&sparams=expire%2Cei%2Cip%2Cid%2Caitags%2Csource%2Crequiressl%2Cmime%2Cgir%2Cclen%2Cdur%2Clmt&sig=ALgxI2wwRQIhAOVC8xEmKAR6l44uIpmcNF01V_DqXZgpHdy4grRCEqGsAiApwXnCUnRkk2TK6v7dKztC8M-Rz4Q53dP_bevsU94Fuw%3D%3D&lsparams=mm%2Cmn%2Cms%2Cmv%2Cmvi%2Cpl%2Cinitcwndbps&lsig=AHylml4wRQIhALfDth5wbLngxVSJRuRMR1H1JNniU1V4CoFDsWDAzxIkAiAU4Xx3ZGd1Z-1Oj-d0ZmVhccwGDodPwdabQYQHw07_eg%3D%3D&ratebypass=yes", "player_url": "/yts/jsbin/player_ias-vfl3cxFuT/en_US/base.js", "ext": "mp4", "height": 144, "format_note": "144p", "vcodec": "avc1.4d400c", "filesize": 13840073, "tbr": 111.069, "width": 256, "fps": 24, "quality": -1, "acodec": "none", "downloader_options": {"http_chunk_size": 10485760}, "format": "160 - 256x144 (144p)", "protocol": "https", "http_headers": {"User-Agent": "Mozilla/5.0 (Windows NT 10.0; Win64; x64) AppleWebKit/537.36 (KHTML, like Gecko) Chrome/73.0.3639.0 Safari/537.36", "Accept-Charset": "ISO-8859-1,utf-8;q=0.7,*;q=0.7", "Accept": "text/html,application/xhtml+xml,application/xml;q=0.9,*/*;q=0.8", "Accept-Encoding": "gzip, deflate", "Accept-Language": "en-us,en;q=0.5"}}, {"format_id": "278", "url": "https://r5---sn-qxo7rn7l.googlevideo.com/videoplayback?expire=1565151721&ei=if1JXdmwHIy5igT5kKnIDg&ip=75.148.115.129&id=o-APep3WUvnBIUQs-4o6_aqmYdw6AUcs2c1j2F-6Jz7WsO&itag=278&aitags=133%2C134%2C135%2C136%2C137%2C160%2C242%2C243%2C244%2C247%2C248%2C278%2C394%2C395%2C396%2C397%2C398&source=youtube&requiressl=yes&mm=31%2C29&mn=sn-qxo7rn7l%2Csn-qxoedn7e&ms=au%2Crdu&mv=m&mvi=4&pl=20&initcwndbps=2182500&mime=video%2Fwebm&gir=yes&clen=20902873&dur=1630.170&lmt=1558647789366503&mt=1565129957&fvip=5&keepalive=yes&c=WEB&txp=5535332&sparams=expire%2Cei%2Cip%2Cid%2Caitags%2Csource%2Crequiressl%2Cmime%2Cgir%2Cclen%2Cdur%2Clmt&sig=ALgxI2wwRAIgEZp82DetIqlH5xTtqG3Eyjzpx-mhVgzxFghqXi9UKcQCIFSHdXdXzWAUZTXd1DXoz7sUwFxRuVau2h_yUql-1-kW&lsparams=mm%2Cmn%2Cms%2Cmv%2Cmvi%2Cpl%2Cinitcwndbps&lsig=AHylml4wRQIhALfDth5wbLngxVSJRuRMR1H1JNniU1V4CoFDsWDAzxIkAiAU4Xx3ZGd1Z-1Oj-d0ZmVhccwGDodPwdabQYQHw07_eg%3D%3D&ratebypass=yes", "player_url": "/yts/jsbin/player_ias-vfl3cxFuT/en_US/base.js", "ext": "webm", "height": 144, "format_note": "144p", "container": "webm", "vcodec": "vp9", "filesize": 20902873, "tbr": 144.421, "width": 256, "fps": 24, "quality": -1, "acodec": "none", "downloader_options": {"http_chunk_size": 10485760}, "format": "278 - 256x144 (144p)", "protocol": "https", "http_headers": {"User-Agent": "Mozilla/5.0 (Windows NT 10.0; Win64; x64) AppleWebKit/537.36 (KHTML, like Gecko) Chrome/73.0.3639.0 Safari/537.36", "Accept-Charset": "ISO-8859-1,utf-8;q=0.7,*;q=0.7", "Accept": "text/html,application/xhtml+xml,application/xml;q=0.9,*/*;q=0.8", "Accept-Encoding": "gzip, deflate", "Accept-Language": "en-us,en;q=0.5"}}, {"format_id": "395", "url": "https://r5---sn-qxo7rn7l.googlevideo.com/videoplayback?expire=1565151721&ei=if1JXdmwHIy5igT5kKnIDg&ip=75.148.115.129&id=o-APep3WUvnBIUQs-4o6_aqmYdw6AUcs2c1j2F-6Jz7WsO&itag=395&aitags=133%2C134%2C135%2C136%2C137%2C160%2C242%2C243%2C244%2C247%2C248%2C278%2C394%2C395%2C396%2C397%2C398&source=youtube&requiressl=yes&mm=31%2C29&mn=sn-qxo7rn7l%2Csn-qxoedn7e&ms=au%2Crdu&mv=m&mvi=4&pl=20&initcwndbps=2182500&mime=video%2Fmp4&gir=yes&clen=29528770&dur=1630.170&lmt=1553824130623381&mt=1565129957&fvip=5&keepalive=yes&c=WEB&txp=5531432&sparams=expire%2Cei%2Cip%2Cid%2Caitags%2Csource%2Crequiressl%2Cmime%2Cgir%2Cclen%2Cdur%2Clmt&sig=ALgxI2wwRgIhAIzCed4fwim-xASJDzdWCYte-g_ByaerVKG18aHYNccfAiEAr8-vYTWxGi6jYwfCPkUOAwslkDkGacdQ_se8DiEdzm8%3D&lsparams=mm%2Cmn%2Cms%2Cmv%2Cmvi%2Cpl%2Cinitcwndbps&lsig=AHylml4wRQIhALfDth5wbLngxVSJRuRMR1H1JNniU1V4CoFDsWDAzxIkAiAU4Xx3ZGd1Z-1Oj-d0ZmVhccwGDodPwdabQYQHw07_eg%3D%3D&ratebypass=yes", "player_url": "/yts/jsbin/player_ias-vfl3cxFuT/en_US/base.js", "acodec": "none", "vcodec": "av01.0.05M.08", "filesize": 29528770, "tbr": 200.933, "width": 426, "height": 240, "fps": 24, "format_note": "240p", "quality": -1, "ext": "mp4", "downloader_options": {"http_chunk_size": 10485760}, "format": "395 - 426x240 (240p)", "protocol": "https", "http_headers": {"User-Agent": "Mozilla/5.0 (Windows NT 10.0; Win64; x64) AppleWebKit/537.36 (KHTML, like Gecko) Chrome/73.0.3639.0 Safari/537.36", "Accept-Charset": "ISO-8859-1,utf-8;q=0.7,*;q=0.7", "Accept": "text/html,application/xhtml+xml,application/xml;q=0.9,*/*;q=0.8", "Accept-Encoding": "gzip, deflate", "Accept-Language": "en-us,en;q=0.5"}}, {"format_id": "242", "url": "https://r5---sn-qxo7rn7l.googlevideo.com/videoplayback?expire=1565151721&ei=if1JXdmwHIy5igT5kKnIDg&ip=75.148.115.129&id=o-APep3WUvnBIUQs-4o6_aqmYdw6AUcs2c1j2F-6Jz7WsO&itag=242&aitags=133%2C134%2C135%2C136%2C137%2C160%2C242%2C243%2C244%2C247%2C248%2C278%2C394%2C395%2C396%2C397%2C398&source=youtube&requiressl=yes&mm=31%2C29&mn=sn-qxo7rn7l%2Csn-qxoedn7e&ms=au%2Crdu&mv=m&mvi=4&pl=20&initcwndbps=2182500&mime=video%2Fwebm&gir=yes&clen=29355793&dur=1630.170&lmt=1558647954568467&mt=1565129957&fvip=5&keepalive=yes&c=WEB&txp=5535332&sparams=expire%2Cei%2Cip%2Cid%2Caitags%2Csource%2Crequiressl%2Cmime%2Cgir%2Cclen%2Cdur%2Clmt&sig=ALgxI2wwRAIgYggarNj_yWs0qKOvjD2tlBN3VX7J7zM9t5H2zgTxL28CIA4W8YffohrLM_pReIKlJFqC40rWRs4qVZI8x45FhN7G&lsparams=mm%2Cmn%2Cms%2Cmv%2Cmvi%2Cpl%2Cinitcwndbps&lsig=AHylml4wRQIhALfDth5wbLngxVSJRuRMR1H1JNniU1V4CoFDsWDAzxIkAiAU4Xx3ZGd1Z-1Oj-d0ZmVhccwGDodPwdabQYQHw07_eg%3D%3D&ratebypass=yes", "player_url": "/yts/jsbin/player_ias-vfl3cxFuT/en_US/base.js", "ext": "webm", "height": 240, "format_note": "240p", "vcodec": "vp9", "filesize": 29355793, "tbr": 220.625, "width": 426, "fps": 24, "quality": -1, "acodec": "none", "downloader_options": {"http_chunk_size": 10485760}, "format": "242 - 426x240 (240p)", "protocol": "https", "http_headers": {"User-Agent": "Mozilla/5.0 (Windows NT 10.0; Win64; x64) AppleWebKit/537.36 (KHTML, like Gecko) Chrome/73.0.3639.0 Safari/537.36", "Accept-Charset": "ISO-8859-1,utf-8;q=0.7,*;q=0.7", "Accept": "text/html,application/xhtml+xml,application/xml;q=0.9,*/*;q=0.8", "Accept-Encoding": "gzip, deflate", "Accept-Language": "en-us,en;q=0.5"}}, {"format_id": "133", "url": "https://r5---sn-qxo7rn7l.googlevideo.com/videoplayback?expire=1565151721&ei=if1JXdmwHIy5igT5kKnIDg&ip=75.148.115.129&id=o-APep3WUvnBIUQs-4o6_aqmYdw6AUcs2c1j2F-6Jz7WsO&itag=133&aitags=133%2C134%2C135%2C136%2C137%2C160%2C242%2C243%2C244%2C247%2C248%2C278%2C394%2C395%2C396%2C397%2C398&source=youtube&requiressl=yes&mm=31%2C29&mn=sn-qxo7rn7l%2Csn-qxoedn7e&ms=au%2Crdu&mv=m&mvi=4&pl=20&initcwndbps=2182500&mime=video%2Fmp4&gir=yes&clen=26478024&dur=1630.170&lmt=1553531072973347&mt=1565129957&fvip=5&keepalive=yes&c=WEB&txp=4535432&sparams=expire%2Cei%2Cip%2Cid%2Caitags%2Csource%2Crequiressl%2Cmime%2Cgir%2Cclen%2Cdur%2Clmt&sig=ALgxI2wwRgIhAMaoxaM-JHyGHKttL54dkIa9pp2w19YHvkQQBUKWbWk4AiEA750d0JvQtsudlNE3bTvq3zzhq99hAYX5jOBlyQz0It0%3D&lsparams=mm%2Cmn%2Cms%2Cmv%2Cmvi%2Cpl%2Cinitcwndbps&lsig=AHylml4wRQIhALfDth5wbLngxVSJRuRMR1H1JNniU1V4CoFDsWDAzxIkAiAU4Xx3ZGd1Z-1Oj-d0ZmVhccwGDodPwdabQYQHw07_eg%3D%3D&ratebypass=yes", "player_url": "/yts/jsbin/player_ias-vfl3cxFuT/en_US/base.js", "ext": "mp4", "height": 240, "format_note": "240p", "vcodec": "avc1.4d4015", "filesize": 26478024, "tbr": 271.595, "width": 426, "fps": 24, "quality": -1, "acodec": "none", "downloader_options": {"http_chunk_size": 10485760}, "format": "133 - 426x240 (240p)", "protocol": "https", "http_headers": {"User-Agent": "Mozilla/5.0 (Windows NT 10.0; Win64; x64) AppleWebKit/537.36 (KHTML, like Gecko) Chrome/73.0.3639.0 Safari/537.36", "Accept-Charset": "ISO-8859-1,utf-8;q=0.7,*;q=0.7", "Accept": "text/html,application/xhtml+xml,application/xml;q=0.9,*/*;q=0.8", "Accept-Encoding": "gzip, deflate", "Accept-Language": "en-us,en;q=0.5"}}, {"format_id": "396", "url": "https://r5---sn-qxo7rn7l.googlevideo.com/videoplayback?expire=1565151721&ei=if1JXdmwHIy5igT5kKnIDg&ip=75.148.115.129&id=o-APep3WUvnBIUQs-4o6_aqmYdw6AUcs2c1j2F-6Jz7WsO&itag=396&aitags=133%2C134%2C135%2C136%2C137%2C160%2C242%2C243%2C244%2C247%2C248%2C278%2C394%2C395%2C396%2C397%2C398&source=youtube&requiressl=yes&mm=31%2C29&mn=sn-qxo7rn7l%2Csn-qxoedn7e&ms=au%2Crdu&mv=m&mvi=4&pl=20&initcwndbps=2182500&mime=video%2Fmp4&gir=yes&clen=52551701&dur=1630.170&lmt=1553872098287669&mt=1565129957&fvip=5&keepalive=yes&c=WEB&txp=5531432&sparams=expire%2Cei%2Cip%2Cid%2Caitags%2Csource%2Crequiressl%2Cmime%2Cgir%2Cclen%2Cdur%2Clmt&sig=ALgxI2wwRAIgaKjLWgGS41EHRM_3Ahry4VpjWY6TdC_SQe9VDtRp0zwCIB30A1HjqhQi5rTbX-rfJUc9PY8I71LKBTxoOfzOkoNx&lsparams=mm%2Cmn%2Cms%2Cmv%2Cmvi%2Cpl%2Cinitcwndbps&lsig=AHylml4wRQIhALfDth5wbLngxVSJRuRMR1H1JNniU1V4CoFDsWDAzxIkAiAU4Xx3ZGd1Z-1Oj-d0ZmVhccwGDodPwdabQYQHw07_eg%3D%3D&ratebypass=yes", "player_url": "/yts/jsbin/player_ias-vfl3cxFuT/en_US/base.js", "acodec": "none", "vcodec": "av01.0.05M.08", "filesize": 52551701, "tbr": 363.91, "width": 640, "height": 360, "fps": 24, "format_note": "360p", "quality": -1, "ext": "mp4", "downloader_options": {"http_chunk_size": 10485760}, "format": "396 - 640x360 (360p)", "protocol": "https", "http_headers": {"User-Agent": "Mozilla/5.0 (Windows NT 10.0; Win64; x64) AppleWebKit/537.36 (KHTML, like Gecko) Chrome/73.0.3639.0 Safari/537.36", "Accept-Charset": "ISO-8859-1,utf-8;q=0.7,*;q=0.7", "Accept": "text/html,application/xhtml+xml,application/xml;q=0.9,*/*;q=0.8", "Accept-Encoding": "gzip, deflate", "Accept-Language": "en-us,en;q=0.5"}}, {"format_id": "243", "url": "https://r5---sn-qxo7rn7l.googlevideo.com/videoplayback?expire=1565151721&ei=if1JXdmwHIy5igT5kKnIDg&ip=75.148.115.129&id=o-APep3WUvnBIUQs-4o6_aqmYdw6AUcs2c1j2F-6Jz7WsO&itag=243&aitags=133%2C134%2C135%2C136%2C137%2C160%2C242%2C243%2C244%2C247%2C248%2C278%2C394%2C395%2C396%2C397%2C398&source=youtube&requiressl=yes&mm=31%2C29&mn=sn-qxo7rn7l%2Csn-qxoedn7e&ms=au%2Crdu&mv=m&mvi=4&pl=20&initcwndbps=2182500&mime=video%2Fwebm&gir=yes&clen=51057528&dur=1630.170&lmt=1558647896198524&mt=1565129957&fvip=5&keepalive=yes&c=WEB&txp=5535332&sparams=expire%2Cei%2Cip%2Cid%2Caitags%2Csource%2Crequiressl%2Cmime%2Cgir%2Cclen%2Cdur%2Clmt&sig=ALgxI2wwRQIgeJXplzSHJ4NbJVLiAFHxi4G7r2gndNDJ3Dda-NmXQ8oCIQDQW87r7VEMu4ZBR3woxpIIA0RgZkSZc9gyA7Q0byldtA%3D%3D&lsparams=mm%2Cmn%2Cms%2Cmv%2Cmvi%2Cpl%2Cinitcwndbps&lsig=AHylml4wRQIhALfDth5wbLngxVSJRuRMR1H1JNniU1V4CoFDsWDAzxIkAiAU4Xx3ZGd1Z-1Oj-d0ZmVhccwGDodPwdabQYQHw07_eg%3D%3D&ratebypass=yes", "player_url": "/yts/jsbin/player_ias-vfl3cxFuT/en_US/base.js", "ext": "webm", "height": 360, "format_note": "360p", "vcodec": "vp9", "filesize": 51057528, "tbr": 406.887, "width": 640, "fps": 24, "quality": -1, "acodec": "none", "downloader_options": {"http_chunk_size": 10485760}, "format": "243 - 640x360 (360p)", "protocol": "https", "http_headers": {"User-Agent": "Mozilla/5.0 (Windows NT 10.0; Win64; x64) AppleWebKit/537.36 (KHTML, like Gecko) Chrome/73.0.3639.0 Safari/537.36", "Accept-Charset": "ISO-8859-1,utf-8;q=0.7,*;q=0.7", "Accept": "text/html,application/xhtml+xml,application/xml;q=0.9,*/*;q=0.8", "Accept-Encoding": "gzip, deflate", "Accept-Language": "en-us,en;q=0.5"}}, {"format_id": "134", "url": "https://r5---sn-qxo7rn7l.googlevideo.com/videoplayback?expire=1565151721&ei=if1JXdmwHIy5igT5kKnIDg&ip=75.148.115.129&id=o-APep3WUvnBIUQs-4o6_aqmYdw6AUcs2c1j2F-6Jz7WsO&itag=134&aitags=133%2C134%2C135%2C136%2C137%2C160%2C242%2C243%2C244%2C247%2C248%2C278%2C394%2C395%2C396%2C397%2C398&source=youtube&requiressl=yes&mm=31%2C29&mn=sn-qxo7rn7l%2Csn-qxoedn7e&ms=au%2Crdu&mv=m&mvi=4&pl=20&initcwndbps=2182500&mime=video%2Fmp4&gir=yes&clen=48256045&dur=1630.170&lmt=1553531080883703&mt=1565129957&fvip=5&keepalive=yes&c=WEB&txp=4535432&sparams=expire%2Cei%2Cip%2Cid%2Caitags%2Csource%2Crequiressl%2Cmime%2Cgir%2Cclen%2Cdur%2Clmt&sig=ALgxI2wwRAIgVlLl7Dyx15UU-uy4M16R9oj9Xriv63M2bfp2nx2td9gCIBWFvkOl9HsLd0naUMtJbw9JiTf4NHJSP2g08MmzlsWG&lsparams=mm%2Cmn%2Cms%2Cmv%2Cmvi%2Cpl%2Cinitcwndbps&lsig=AHylml4wRQIhALfDth5wbLngxVSJRuRMR1H1JNniU1V4CoFDsWDAzxIkAiAU4Xx3ZGd1Z-1Oj-d0ZmVhccwGDodPwdabQYQHw07_eg%3D%3D&ratebypass=yes", "player_url": "/yts/jsbin/player_ias-vfl3cxFuT/en_US/base.js", "ext": "mp4", "height": 360, "format_note": "360p", "vcodec": "avc1.4d401e", "filesize": 48256045, "tbr": 589.162, "width": 640, "fps": 24, "quality": -1, "acodec": "none", "downloader_options": {"http_chunk_size": 10485760}, "format": "134 - 640x360 (360p)", "protocol": "https", "http_headers": {"User-Agent": "Mozilla/5.0 (Windows NT 10.0; Win64; x64) AppleWebKit/537.36 (KHTML, like Gecko) Chrome/73.0.3639.0 Safari/537.36", "Accept-Charset": "ISO-8859-1,utf-8;q=0.7,*;q=0.7", "Accept": "text/html,application/xhtml+xml,application/xml;q=0.9,*/*;q=0.8", "Accept-Encoding": "gzip, deflate", "Accept-Language": "en-us,en;q=0.5"}}, {"format_id": "397", "url": "https://r5---sn-qxo7rn7l.googlevideo.com/videoplayback?expire=1565151721&ei=if1JXdmwHIy5igT5kKnIDg&ip=75.148.115.129&id=o-APep3WUvnBIUQs-4o6_aqmYdw6AUcs2c1j2F-6Jz7WsO&itag=397&aitags=133%2C134%2C135%2C136%2C137%2C160%2C242%2C243%2C244%2C247%2C248%2C278%2C394%2C395%2C396%2C397%2C398&source=youtube&requiressl=yes&mm=31%2C29&mn=sn-qxo7rn7l%2Csn-qxoedn7e&ms=au%2Crdu&mv=m&mvi=4&pl=20&initcwndbps=2182500&mime=video%2Fmp4&gir=yes&clen=91358976&dur=1630.170&lmt=1553838075450442&mt=1565129957&fvip=5&keepalive=yes&c=WEB&txp=5531432&sparams=expire%2Cei%2Cip%2Cid%2Caitags%2Csource%2Crequiressl%2Cmime%2Cgir%2Cclen%2Cdur%2Clmt&sig=ALgxI2wwRQIhAKV8ss-BjI_Igex20Xcfsa4r49NBjaFEDgqPJp7zxox2AiBw5yqArMu1g_12YLEhqmrqf5BoJBM6nT94cFsXjunHPg%3D%3D&lsparams=mm%2Cmn%2Cms%2Cmv%2Cmvi%2Cpl%2Cinitcwndbps&lsig=AHylml4wRQIhALfDth5wbLngxVSJRuRMR1H1JNniU1V4CoFDsWDAzxIkAiAU4Xx3ZGd1Z-1Oj-d0ZmVhccwGDodPwdabQYQHw07_eg%3D%3D&ratebypass=yes", "player_url": "/yts/jsbin/player_ias-vfl3cxFuT/en_US/base.js", "acodec": "none", "vcodec": "av01.0.05M.08", "filesize": 91358976, "tbr": 645.415, "width": 854, "height": 480, "fps": 24, "format_note": "480p", "quality": -1, "ext": "mp4", "downloader_options": {"http_chunk_size": 10485760}, "format": "397 - 854x480 (480p)", "protocol": "https", "http_headers": {"User-Agent": "Mozilla/5.0 (Windows NT 10.0; Win64; x64) AppleWebKit/537.36 (KHTML, like Gecko) Chrome/73.0.3639.0 Safari/537.36", "Accept-Charset": "ISO-8859-1,utf-8;q=0.7,*;q=0.7", "Accept": "text/html,application/xhtml+xml,application/xml;q=0.9,*/*;q=0.8", "Accept-Encoding": "gzip, deflate", "Accept-Language": "en-us,en;q=0.5"}}, {"format_id": "244", "url": "https://r5---sn-qxo7rn7l.googlevideo.com/videoplayback?expire=1565151721&ei=if1JXdmwHIy5igT5kKnIDg&ip=75.148.115.129&id=o-APep3WUvnBIUQs-4o6_aqmYdw6AUcs2c1j2F-6Jz7WsO&itag=244&aitags=133%2C134%2C135%2C136%2C137%2C160%2C242%2C243%2C244%2C247%2C248%2C278%2C394%2C395%2C396%2C397%2C398&source=youtube&requiressl=yes&mm=31%2C29&mn=sn-qxo7rn7l%2Csn-qxoedn7e&ms=au%2Crdu&mv=m&mvi=4&pl=20&initcwndbps=2182500&mime=video%2Fwebm&gir=yes&clen=76413350&dur=1630.170&lmt=1558647853804523&mt=1565129957&fvip=5&keepalive=yes&c=WEB&txp=5535332&sparams=expire%2Cei%2Cip%2Cid%2Caitags%2Csource%2Crequiressl%2Cmime%2Cgir%2Cclen%2Cdur%2Clmt&sig=ALgxI2wwRAIgSGkE9cnIHqjG8rvEOZ5goNRmtLi7wI8NMePvc71E_G4CIFaBG6vxqVERT7dFp-9jdzlWeyMB3aDfKJ_uQdGnhwgQ&lsparams=mm%2Cmn%2Cms%2Cmv%2Cmvi%2Cpl%2Cinitcwndbps&lsig=AHylml4wRQIhALfDth5wbLngxVSJRuRMR1H1JNniU1V4CoFDsWDAzxIkAiAU4Xx3ZGd1Z-1Oj-d0ZmVhccwGDodPwdabQYQHw07_eg%3D%3D&ratebypass=yes", "player_url": "/yts/jsbin/player_ias-vfl3cxFuT/en_US/base.js", "ext": "webm", "height": 480, "format_note": "480p", "vcodec": "vp9", "filesize": 76413350, "tbr": 746.128, "width": 854, "fps": 24, "quality": -1, "acodec": "none", "downloader_options": {"http_chunk_size": 10485760}, "format": "244 - 854x480 (480p)", "protocol": "https", "http_headers": {"User-Agent": "Mozilla/5.0 (Windows NT 10.0; Win64; x64) AppleWebKit/537.36 (KHTML, like Gecko) Chrome/73.0.3639.0 Safari/537.36", "Accept-Charset": "ISO-8859-1,utf-8;q=0.7,*;q=0.7", "Accept": "text/html,application/xhtml+xml,application/xml;q=0.9,*/*;q=0.8", "Accept-Encoding": "gzip, deflate", "Accept-Language": "en-us,en;q=0.5"}}, {"format_id": "135", "url": "https://r5---sn-qxo7rn7l.googlevideo.com/videoplayback?expire=1565151721&ei=if1JXdmwHIy5igT5kKnIDg&ip=75.148.115.129&id=o-APep3WUvnBIUQs-4o6_aqmYdw6AUcs2c1j2F-6Jz7WsO&itag=135&aitags=133%2C134%2C135%2C136%2C137%2C160%2C242%2C243%2C244%2C247%2C248%2C278%2C394%2C395%2C396%2C397%2C398&source=youtube&requiressl=yes&mm=31%2C29&mn=sn-qxo7rn7l%2Csn-qxoedn7e&ms=au%2Crdu&mv=m&mvi=4&pl=20&initcwndbps=2182500&mime=video%2Fmp4&gir=yes&clen=72337565&dur=1630.170&lmt=1553531103721036&mt=1565129957&fvip=5&keepalive=yes&c=WEB&txp=4535432&sparams=expire%2Cei%2Cip%2Cid%2Caitags%2Csource%2Crequiressl%2Cmime%2Cgir%2Cclen%2Cdur%2Clmt&sig=ALgxI2wwRQIhAPcfPkslvShERK_FMH51JkV9vaSbF9Txf20Sb-ViZ43dAiAejihIjlHKkU7JeCt10HgQfi-K0fNiioBqTvzsZ5VViw%3D%3D&lsparams=mm%2Cmn%2Cms%2Cmv%2Cmvi%2Cpl%2Cinitcwndbps&lsig=AHylml4wRQIhALfDth5wbLngxVSJRuRMR1H1JNniU1V4CoFDsWDAzxIkAiAU4Xx3ZGd1Z-1Oj-d0ZmVhccwGDodPwdabQYQHw07_eg%3D%3D&ratebypass=yes", "player_url": "/yts/jsbin/player_ias-vfl3cxFuT/en_US/base.js", "ext": "mp4", "height": 480, "format_note": "480p", "vcodec": "avc1.4d401e", "filesize": 72337565, "tbr": 938.382, "width": 854, "fps": 24, "quality": -1, "acodec": "none", "downloader_options": {"http_chunk_size": 10485760}, "format": "135 - 854x480 (480p)", "protocol": "https", "http_headers": {"User-Agent": "Mozilla/5.0 (Windows NT 10.0; Win64; x64) AppleWebKit/537.36 (KHTML, like Gecko) Chrome/73.0.3639.0 Safari/537.36", "Accept-Charset": "ISO-8859-1,utf-8;q=0.7,*;q=0.7", "Accept": "text/html,application/xhtml+xml,application/xml;q=0.9,*/*;q=0.8", "Accept-Encoding": "gzip, deflate", "Accept-Language": "en-us,en;q=0.5"}}, {"format_id": "398", "url": "https://r5---sn-qxo7rn7l.googlevideo.com/videoplayback?expire=1565151721&ei=if1JXdmwHIy5igT5kKnIDg&ip=75.148.115.129&id=o-APep3WUvnBIUQs-4o6_aqmYdw6AUcs2c1j2F-6Jz7WsO&itag=398&aitags=133%2C134%2C135%2C136%2C137%2C160%2C242%2C243%2C244%2C247%2C248%2C278%2C394%2C395%2C396%2C397%2C398&source=youtube&requiressl=yes&mm=31%2C29&mn=sn-qxo7rn7l%2Csn-qxoedn7e&ms=au%2Crdu&mv=m&mvi=4&pl=20&initcwndbps=2182500&mime=video%2Fmp4&gir=yes&clen=189870408&dur=1630.170&lmt=1553869882330281&mt=1565129957&fvip=5&keepalive=yes&c=WEB&txp=5531432&sparams=expire%2Cei%2Cip%2Cid%2Caitags%2Csource%2Crequiressl%2Cmime%2Cgir%2Cclen%2Cdur%2Clmt&sig=ALgxI2wwRAIgerpleHkQ5UO20XpF2ijOEnmBpJ3327s5MLTowJ1TiG8CIAz3C03QDHBPxKtz7cJOufGg2h2vzbpxtMDIpn27eX6Q&lsparams=mm%2Cmn%2Cms%2Cmv%2Cmvi%2Cpl%2Cinitcwndbps&lsig=AHylml4wRQIhALfDth5wbLngxVSJRuRMR1H1JNniU1V4CoFDsWDAzxIkAiAU4Xx3ZGd1Z-1Oj-d0ZmVhccwGDodPwdabQYQHw07_eg%3D%3D&ratebypass=yes", "player_url": "/yts/jsbin/player_ias-vfl3cxFuT/en_US/base.js", "filesize": 189870408, "tbr": 1308.865, "width": 1280, "height": 720, "fps": 24, "format_note": "720p", "quality": -1, "ext": "mp4", "vcodec": "av01.0.05M.08", "acodec": "none", "downloader_options": {"http_chunk_size": 10485760}, "format": "398 - 1280x720 (720p)", "protocol": "https", "http_headers": {"User-Agent": "Mozilla/5.0 (Windows NT 10.0; Win64; x64) AppleWebKit/537.36 (KHTML, like Gecko) Chrome/73.0.3639.0 Safari/537.36", "Accept-Charset": "ISO-8859-1,utf-8;q=0.7,*;q=0.7", "Accept": "text/html,application/xhtml+xml,application/xml;q=0.9,*/*;q=0.8", "Accept-Encoding": "gzip, deflate", "Accept-Language": "en-us,en;q=0.5"}}, {"format_id": "136", "url": "https://r5---sn-qxo7rn7l.googlevideo.com/videoplayback?expire=1565151721&ei=if1JXdmwHIy5igT5kKnIDg&ip=75.148.115.129&id=o-APep3WUvnBIUQs-4o6_aqmYdw6AUcs2c1j2F-6Jz7WsO&itag=136&aitags=133%2C134%2C135%2C136%2C137%2C160%2C242%2C243%2C244%2C247%2C248%2C278%2C394%2C395%2C396%2C397%2C398&source=youtube&requiressl=yes&mm=31%2C29&mn=sn-qxo7rn7l%2Csn-qxoedn7e&ms=au%2Crdu&mv=m&mvi=4&pl=20&initcwndbps=2182500&mime=video%2Fmp4&gir=yes&clen=113876477&dur=1630.170&lmt=1553531122846245&mt=1565129957&fvip=5&keepalive=yes&c=WEB&txp=4535432&sparams=expire%2Cei%2Cip%2Cid%2Caitags%2Csource%2Crequiressl%2Cmime%2Cgir%2Cclen%2Cdur%2Clmt&sig=ALgxI2wwRgIhAKDO65UQdDnl48bnEQnShR5gfpBytbm6p3PVCM3OpNi2AiEAlANgcQqF1BYs06jyzX_NF4KbsAi8sAsGx_9dQIxajIg%3D&lsparams=mm%2Cmn%2Cms%2Cmv%2Cmvi%2Cpl%2Cinitcwndbps&lsig=AHylml4wRQIhALfDth5wbLngxVSJRuRMR1H1JNniU1V4CoFDsWDAzxIkAiAU4Xx3ZGd1Z-1Oj-d0ZmVhccwGDodPwdabQYQHw07_eg%3D%3D&ratebypass=yes", "player_url": "/yts/jsbin/player_ias-vfl3cxFuT/en_US/base.js", "ext": "mp4", "height": 720, "format_note": "720p", "vcodec": "avc1.4d401f", "filesize": 113876477, "tbr": 1463.834, "width": 1280, "fps": 24, "quality": -1, "acodec": "none", "downloader_options": {"http_chunk_size": 10485760}, "format": "136 - 1280x720 (720p)", "protocol": "https", "http_headers": {"User-Agent": "Mozilla/5.0 (Windows NT 10.0; Win64; x64) AppleWebKit/537.36 (KHTML, like Gecko) Chrome/73.0.3639.0 Safari/537.36", "Accept-Charset": "ISO-8859-1,utf-8;q=0.7,*;q=0.7", "Accept": "text/html,application/xhtml+xml,application/xml;q=0.9,*/*;q=0.8", "Accept-Encoding": "gzip, deflate", "Accept-Language": "en-us,en;q=0.5"}}, {"format_id": "247", "url": "https://r5---sn-qxo7rn7l.googlevideo.com/videoplayback?expire=1565151721&ei=if1JXdmwHIy5igT5kKnIDg&ip=75.148.115.129&id=o-APep3WUvnBIUQs-4o6_aqmYdw6AUcs2c1j2F-6Jz7WsO&itag=247&aitags=133%2C134%2C135%2C136%2C137%2C160%2C242%2C243%2C244%2C247%2C248%2C278%2C394%2C395%2C396%2C397%2C398&source=youtube&requiressl=yes&mm=31%2C29&mn=sn-qxo7rn7l%2Csn-qxoedn7e&ms=au%2Crdu&mv=m&mvi=4&pl=20&initcwndbps=2182500&mime=video%2Fwebm&gir=yes&clen=127555020&dur=1630.170&lmt=1558648039703601&mt=1565129957&fvip=5&keepalive=yes&c=WEB&txp=5535332&sparams=expire%2Cei%2Cip%2Cid%2Caitags%2Csource%2Crequiressl%2Cmime%2Cgir%2Cclen%2Cdur%2Clmt&sig=ALgxI2wwRgIhAO3RsVI8C3ugWRCYzK_gLEoeI64M5i4SzUtCMnG2cfMdAiEAgWEB04Ablygix8MPzP5PE2qIrZdh9Y1stjLo7tte7F4%3D&lsparams=mm%2Cmn%2Cms%2Cmv%2Cmvi%2Cpl%2Cinitcwndbps&lsig=AHylml4wRQIhALfDth5wbLngxVSJRuRMR1H1JNniU1V4CoFDsWDAzxIkAiAU4Xx3ZGd1Z-1Oj-d0ZmVhccwGDodPwdabQYQHw07_eg%3D%3D&ratebypass=yes", "player_url": "/yts/jsbin/player_ias-vfl3cxFuT/en_US/base.js", "ext": "webm", "height": 720, "format_note": "720p", "vcodec": "vp9", "filesize": 127555020, "tbr": 1488.58, "width": 1280, "fps": 24, "quality": -1, "acodec": "none", "downloader_options": {"http_chunk_size": 10485760}, "format": "247 - 1280x720 (720p)", "protocol": "https", "http_headers": {"User-Agent": "Mozilla/5.0 (Windows NT 10.0; Win64; x64) AppleWebKit/537.36 (KHTML, like Gecko) Chrome/73.0.3639.0 Safari/537.36", "Accept-Charset": "ISO-8859-1,utf-8;q=0.7,*;q=0.7", "Accept": "text/html,application/xhtml+xml,application/xml;q=0.9,*/*;q=0.8", "Accept-Encoding": "gzip, deflate", "Accept-Language": "en-us,en;q=0.5"}}, {"format_id": "248", "url": "https://r5---sn-qxo7rn7l.googlevideo.com/videoplayback?expire=1565151721&ei=if1JXdmwHIy5igT5kKnIDg&ip=75.148.115.129&id=o-APep3WUvnBIUQs-4o6_aqmYdw6AUcs2c1j2F-6Jz7WsO&itag=248&aitags=133%2C134%2C135%2C136%2C137%2C160%2C242%2C243%2C244%2C247%2C248%2C278%2C394%2C395%2C396%2C397%2C398&source=youtube&requiressl=yes&mm=31%2C29&mn=sn-qxo7rn7l%2Csn-qxoedn7e&ms=au%2Crdu&mv=m&mvi=4&pl=20&initcwndbps=2182500&mime=video%2Fwebm&gir=yes&clen=366867473&dur=1630.170&lmt=1558648448551627&mt=1565129957&fvip=5&keepalive=yes&c=WEB&txp=5535332&sparams=expire%2Cei%2Cip%2Cid%2Caitags%2Csource%2Crequiressl%2Cmime%2Cgir%2Cclen%2Cdur%2Clmt&sig=ALgxI2wwRAIgRwsEt0Ef_T1YcwCz4qAWSkE8N_uKUObk5FA32LLUzJECIDGtItaE9x_6njUbfRxMLQ8FBzMEL_kJhgZz89bJthIi&lsparams=mm%2Cmn%2Cms%2Cmv%2Cmvi%2Cpl%2Cinitcwndbps&lsig=AHylml4wRQIhALfDth5wbLngxVSJRuRMR1H1JNniU1V4CoFDsWDAzxIkAiAU4Xx3ZGd1Z-1Oj-d0ZmVhccwGDodPwdabQYQHw07_eg%3D%3D&ratebypass=yes", "player_url": "/yts/jsbin/player_ias-vfl3cxFuT/en_US/base.js", "ext": "webm", "height": 1080, "format_note": "1080p", "vcodec": "vp9", "filesize": 366867473, "tbr": 2716.382, "width": 1920, "fps": 24, "quality": -1, "acodec": "none", "downloader_options": {"http_chunk_size": 10485760}, "format": "248 - 1920x1080 (1080p)", "protocol": "https", "http_headers": {"User-Agent": "Mozilla/5.0 (Windows NT 10.0; Win64; x64) AppleWebKit/537.36 (KHTML, like Gecko) Chrome/73.0.3639.0 Safari/537.36", "Accept-Charset": "ISO-8859-1,utf-8;q=0.7,*;q=0.7", "Accept": "text/html,application/xhtml+xml,application/xml;q=0.9,*/*;q=0.8", "Accept-Encoding": "gzip, deflate", "Accept-Language": "en-us,en;q=0.5"}}, {"format_id": "137", "url": "https://r5---sn-qxo7rn7l.googlevideo.com/videoplayback?expire=1565151721&ei=if1JXdmwHIy5igT5kKnIDg&ip=75.148.115.129&id=o-APep3WUvnBIUQs-4o6_aqmYdw6AUcs2c1j2F-6Jz7WsO&itag=137&aitags=133%2C134%2C135%2C136%2C137%2C160%2C242%2C243%2C244%2C247%2C248%2C278%2C394%2C395%2C396%2C397%2C398&source=youtube&requiressl=yes&mm=31%2C29&mn=sn-qxo7rn7l%2Csn-qxoedn7e&ms=au%2Crdu&mv=m&mvi=4&pl=20&initcwndbps=2182500&mime=video%2Fmp4&gir=yes&clen=366220969&dur=1630.170&lmt=1553531233752803&mt=1565129957&fvip=5&keepalive=yes&c=WEB&txp=4535432&sparams=expire%2Cei%2Cip%2Cid%2Caitags%2Csource%2Crequiressl%2Cmime%2Cgir%2Cclen%2Cdur%2Clmt&sig=ALgxI2wwRQIgHsLD-HH9wKHWAsmbARzKmu_GFDdBRfOZkBPM8uhztRICIQDHFte0PHI9x1Ey1a934njLt5uhz7liVuQMMwgnFflbNQ%3D%3D&lsparams=mm%2Cmn%2Cms%2Cmv%2Cmvi%2Cpl%2Cinitcwndbps&lsig=AHylml4wRQIhALfDth5wbLngxVSJRuRMR1H1JNniU1V4CoFDsWDAzxIkAiAU4Xx3ZGd1Z-1Oj-d0ZmVhccwGDodPwdabQYQHw07_eg%3D%3D&ratebypass=yes", "player_url": "/yts/jsbin/player_ias-vfl3cxFuT/en_US/base.js", "ext": "mp4", "height": 1080, "format_note": "1080p", "vcodec": "avc1.640028", "filesize": 366220969, "tbr": 4333.227, "width": 1920, "fps": 24, "quality": -1, "acodec": "none", "downloader_options": {"http_chunk_size": 10485760}, "format": "137 - 1920x1080 (1080p)", "protocol": "https", "http_headers": {"User-Agent": "Mozilla/5.0 (Windows NT 10.0; Win64; x64) AppleWebKit/537.36 (KHTML, like Gecko) Chrome/73.0.3639.0 Safari/537.36", "Accept-Charset": "ISO-8859-1,utf-8;q=0.7,*;q=0.7", "Accept": "text/html,application/xhtml+xml,application/xml;q=0.9,*/*;q=0.8", "Accept-Encoding": "gzip, deflate", "Accept-Language": "en-us,en;q=0.5"}}, {"format_id": "43", "url": "https://r5---sn-qxo7rn7l.googlevideo.com/videoplayback?expire=1565151721&ei=if1JXdmwHIy5igT5kKnIDg&ip=75.148.115.129&id=o-APep3WUvnBIUQs-4o6_aqmYdw6AUcs2c1j2F-6Jz7WsO&itag=43&source=youtube&requiressl=yes&mm=31%2C29&mn=sn-qxo7rn7l%2Csn-qxoedn7e&ms=au%2Crdu&mv=m&mvi=4&pl=20&initcwndbps=2182500&mime=video%2Fwebm&gir=yes&clen=161962648&ratebypass=yes&dur=0.000&lmt=1553592750671598&mt=1565129957&fvip=5&c=WEB&txp=5511222&sparams=expire%2Cei%2Cip%2Cid%2Citag%2Csource%2Crequiressl%2Cmime%2Cgir%2Cclen%2Cratebypass%2Cdur%2Clmt&sig=ALgxI2wwRgIhAKHuMX5zFjtbnHpi9H7AryjUiLJinKH1OuM2A7iaJ8ikAiEA1euAO47tzut1UiySJ9NnGuBRwB9lNtubJ-nCupbmdNQ%3D&lsparams=mm%2Cmn%2Cms%2Cmv%2Cmvi%2Cpl%2Cinitcwndbps&lsig=AHylml4wRQIhALfDth5wbLngxVSJRuRMR1H1JNniU1V4CoFDsWDAzxIkAiAU4Xx3ZGd1Z-1Oj-d0ZmVhccwGDodPwdabQYQHw07_eg%3D%3D", "player_url": "/yts/jsbin/player_ias-vfl3cxFuT/en_US/base.js", "ext": "webm", "width": 640, "height": 360, "acodec": "vorbis", "abr": 128, "vcodec": "vp8.0", "asr": null, "filesize": 161962648, "format_note": "medium", "fps": null, "quality": 1, "tbr": null, "format": "43 - 640x360 (medium)", "protocol": "https", "http_headers": {"User-Agent": "Mozilla/5.0 (Windows NT 10.0; Win64; x64) AppleWebKit/537.36 (KHTML, like Gecko) Chrome/73.0.3639.0 Safari/537.36", "Accept-Charset": "ISO-8859-1,utf-8;q=0.7,*;q=0.7", "Accept": "text/html,application/xhtml+xml,application/xml;q=0.9,*/*;q=0.8", "Accept-Encoding": "gzip, deflate", "Accept-Language": "en-us,en;q=0.5"}}, {"format_id": "18", "url": "https://r5---sn-qxo7rn7l.googlevideo.com/videoplayback?expire=1565151721&ei=if1JXdmwHIy5igT5kKnIDg&ip=75.148.115.129&id=o-APep3WUvnBIUQs-4o6_aqmYdw6AUcs2c1j2F-6Jz7WsO&itag=18&source=youtube&requiressl=yes&mm=31%2C29&mn=sn-qxo7rn7l%2Csn-qxoedn7e&ms=au%2Crdu&mv=m&mvi=4&pl=20&initcwndbps=2182500&mime=video%2Fmp4&gir=yes&clen=104309763&ratebypass=yes&dur=1630.273&lmt=1553529855989490&mt=1565129957&fvip=5&c=WEB&txp=4531432&sparams=expire%2Cei%2Cip%2Cid%2Citag%2Csource%2Crequiressl%2Cmime%2Cgir%2Cclen%2Cratebypass%2Cdur%2Clmt&sig=ALgxI2wwRAIgNELR9CSubdYnsaoL3wzsGckNpqzPnNyR2sH5Y3ME8ecCIA2is-T6HQayc-vwo70Rlv7DNjWU7srl6FvoEjSbXFhp&lsparams=mm%2Cmn%2Cms%2Cmv%2Cmvi%2Cpl%2Cinitcwndbps&lsig=AHylml4wRQIhALfDth5wbLngxVSJRuRMR1H1JNniU1V4CoFDsWDAzxIkAiAU4Xx3ZGd1Z-1Oj-d0ZmVhccwGDodPwdabQYQHw07_eg%3D%3D", "player_url": "/yts/jsbin/player_ias-vfl3cxFuT/en_US/base.js", "ext": "mp4", "width": 640, "height": 360, "acodec": "mp4a.40.2", "abr": 96, "vcodec": "avc1.42001E", "asr": 44100, "filesize": 104309763, "format_note": "medium", "fps": null, "quality": 1, "tbr": 511.864, "format": "18 - 640x360 (medium)", "protocol": "https", "http_headers": {"User-Agent": "Mozilla/5.0 (Windows NT 10.0; Win64; x64) AppleWebKit/537.36 (KHTML, like Gecko) Chrome/73.0.3639.0 Safari/537.36", "Accept-Charset": "ISO-8859-1,utf-8;q=0.7,*;q=0.7", "Accept": "text/html,application/xhtml+xml,application/xml;q=0.9,*/*;q=0.8", "Accept-Encoding": "gzip, deflate", "Accept-Language": "en-us,en;q=0.5"}}, {"format_id": "22", "url": "https://r5---sn-qxo7rn7l.googlevideo.com/videoplayback?expire=1565151721&ei=if1JXdmwHIy5igT5kKnIDg&ip=75.148.115.129&id=o-APep3WUvnBIUQs-4o6_aqmYdw6AUcs2c1j2F-6Jz7WsO&itag=22&source=youtube&requiressl=yes&mm=31%2C29&mn=sn-qxo7rn7l%2Csn-qxoedn7e&ms=au%2Crdu&mv=m&mvi=4&pl=20&initcwndbps=2182500&mime=video%2Fmp4&ratebypass=yes&dur=1630.273&lmt=1553531224944081&mt=1565129957&fvip=5&c=WEB&txp=4535432&sparams=expire%2Cei%2Cip%2Cid%2Citag%2Csource%2Crequiressl%2Cmime%2Cratebypass%2Cdur%2Clmt&sig=ALgxI2wwRgIhANOBrvyiq51rB7BNZlDFV9LRTR1kwduhomtCdb2mGct2AiEA2Hiikhg9vInnAh4M9rftU9jypjjJWQv8cCyvQnj6zFk%3D&lsparams=mm%2Cmn%2Cms%2Cmv%2Cmvi%2Cpl%2Cinitcwndbps&lsig=AHylml4wRQIhALfDth5wbLngxVSJRuRMR1H1JNniU1V4CoFDsWDAzxIkAiAU4Xx3ZGd1Z-1Oj-d0ZmVhccwGDodPwdabQYQHw07_eg%3D%3D", "player_url": "/yts/jsbin/player_ias-vfl3cxFuT/en_US/base.js", "ext": "mp4", "width": 1280, "height": 720, "acodec": "mp4a.40.2", "abr": 192, "vcodec": "avc1.64001F", "asr": 44100, "filesize": null, "format_note": "hd720", "fps": null, "quality": 2, "tbr": 687.952, "format": "22 - 1280x720 (hd720)", "protocol": "https", "http_headers": {"User-Agent": "Mozilla/5.0 (Windows NT 10.0; Win64; x64) AppleWebKit/537.36 (KHTML, like Gecko) Chrome/73.0.3639.0 Safari/537.36", "Accept-Charset": "ISO-8859-1,utf-8;q=0.7,*;q=0.7", "Accept": "text/html,application/xhtml+xml,application/xml;q=0.9,*/*;q=0.8", "Accept-Encoding": "gzip, deflate", "Accept-Language": "en-us,en;q=0.5"}}], "is_live": null, "start_time": null, "end_time": null, "series": null, "season_number": null, "episode_number": null, "track": null, "artist": null, "album": null, "release_date": null, "release_year": null, "extractor": "youtube", "webpage_url_basename": "qWAagS_MANg", "extractor_key": "Youtube", "n_entries": 3, "playlist": "Almost Every", "playlist_id": "PLKtIunYVkv_RfNmjLUZmnhtfypjTKI2QV", "playlist_title": "Almost Every", "playlist_uploader": "Bon App\u00e9tit", "playlist_uploader_id": "BonAppetitDotCom", "playlist_index": 2, "thumbnails": [{"url": "https://i.ytimg.com/vi/qWAagS_MANg/maxresdefault.jpg", "id": "0"}], "display_id": "qWAagS_MANg", "format": "137 - 1920x1080 (1080p)+251 - audio only (DASH audio)", "format_id": "137+251", "width": 1920, "height": 1080, "resolution": null, "fps": 24, "vcodec": "avc1.640028", "vbr": null, "stretched_ratio": null, "acodec": "opus", "abr": 160, "ext": "mp4", "fulltitle": "Every Way to Cook an Egg (59 Methods) | Bon App\u00e9tit", "_filename": "Bon App\u00e9tit/Almost Every/2 -- Every Way to Cook an Egg (59 Methods) _ Bon App\u00e9tit.mp4"}